{
  "type_code": "ISTJ",
  "type_name_ar": "اللوجستي الموثوق",
  "type_name_en": "The Logistician",
  "type_tagline_ar": "الموظف الالتزامي المنظّم صاحب الواجب",
  "prevalence_ar": "يُمثّل نحو 12% من الناس، أحد أشيع الأنماط في البيئات المهنية.",
  "summary_for_employee": {
    "headline_ar": "أنت من نمط ISTJ — اللوجستي الموثوق 📋",
    "short_description_ar": "شخصية منضبطة موثوقة، تضع الواجب في المقام الأول. تتميّز بالمنهجية والالتزام بالتفاصيل والإجراءات، وتبني مهنتها على الموثوقية والجودة المستدامة.",
    "top_strengths_ar": [
      "الموثوقية والالتزام",
      "المنهجية في العمل",
      "الدقة في التفاصيل",
      "الانضباط الذاتي",
      "الإخلاص والولاء المهني"
    ],
    "famous_profiles_ar": "من أبرز ذوي هذا النمط: جورج واشنطن، ووارن بافيت، وأنجيلا ميركل."
  },
  "detailed_report_for_admin": {
    "executive_summary_ar": "الموظف من نمط ISTJ — العمود الفقري لأي مؤسسة منظّمة. يتميّز بالموثوقية الاستثنائية والالتزام بالإجراءات والمواعيد. مرشّح ممتاز لأدوار الامتثال والتدقيق وإدارة العقود. قد يواجه تحديات في البيئات الفوضوية أو التي تتطلّب مرونة سريعة، وقد يُقاوم التغيير في بدايته.",
    "swot_analysis_ar": {
      "strengths": {
        "title_ar": "نقاط القوة (S) — داخلية إيجابية",
        "items_ar": [
          "موثوقية استثنائية في تنفيذ المهام الموكلة",
          "منهجية منظّمة في إدارة الوقت والأولويات",
          "التزام صارم بالإجراءات والمعايير",
          "ذاكرة مهنية قوية بالتفاصيل والسوابق",
          "صبر على المهام الطويلة والمتكرّرة"
        ]
      },
      "weaknesses": {
        "title_ar": "نقاط الضعف (W) — داخلية سلبية",
        "items_ar": [
          "صعوبة في التكيّف السريع مع التغييرات",
          "قد يُقاوم الأساليب الجديدة دون اختبارها",
          "تحمّل محدود للعفوية والفوضى",
          "قد يكون متصلّباً في تطبيق القواعد",
          "محدودية في الإبداع والتفكير خارج الصندوق"
        ]
      },
      "opportunities": {
        "title_ar": "الفرص (O) — خارجية إيجابية",
        "items_ar": [
          "مثالي لأدوار الامتثال والحوكمة والتدقيق",
          "فرص في إدارة العقود والملفات الطويلة",
          "دور مرجعي في الإجراءات والتوثيق",
          "قيادة لجان الجودة والامتثال",
          "مسؤولية الأرشفة القانونية للشركة"
        ]
      },
      "threats": {
        "title_ar": "التهديدات (T) — خارجية سلبية",
        "items_ar": [
          "خطر الجمود في بيئات تتطلّب سرعة تكيّف",
          "احتمال الإرهاق من تحمّل أعباء زائدة بسبب موثوقيته",
          "قد يُفسّر التزامه كتصلّب في ثقافات مرنة",
          "خطر فقدان الدافع إذا تعرّض لفوضى مستمرة",
          "احتمال التهميش في النقاشات الإبداعية"
        ]
      }
    },
    "professional_strengths_ar": [
      "الموثوقية: ينجز ما يلتزم به دون تقصير.",
      "المنهجية: يتّبع إجراءات منظّمة ومنطقية.",
      "الدقة: يهتم بالتفاصيل الصغيرة.",
      "الصبر: يتحمّل المهام الطويلة بلا تذمّر.",
      "الذاكرة: يحتفظ بالسوابق والوثائق.",
      "الولاء: مُخلص لعمله ومؤسسته.",
      "الانضباط: يلتزم بالمواعيد والقواعد."
    ],
    "challenges_and_risk_areas_ar": [
      "صعوبة التكيّف مع التغيير السريع.",
      "مقاومة الأساليب الجديدة.",
      "تحمّل محدود للفوضى.",
      "صرامة في تطبيق القواعد.",
      "محدودية في الإبداع.",
      "صعوبة في التعبير العاطفي.",
      "قد يُهمل الجانب الإنساني لصالح الإجراء."
    ],
    "communication_style_ar": {
      "prefers_ar": "التواصل المكتوب الموثّق، التعليمات الواضحة المُفصّلة، الاجتماعات بأجندة ومحضر، المعلومات المدعومة بالوثائق.",
      "avoid_ar": "التغييرات المفاجئة، التعليمات الشفهية العابرة، الفوضى، الاجتماعات بلا هدف."
    },
    "ideal_work_environment_ar": [
      "بيئة منظّمة بإجراءات واضحة.",
      "استقرار وظيفي وثقافة محافظة.",
      "معايير جودة مرتفعة.",
      "هدوء نسبي للتركيز.",
      "احترام التسلسل الوظيفي.",
      "توقّعات محدّدة ومكتوبة."
    ],
    "suitable_roles_ar": [
      "مسؤول الامتثال والحوكمة",
      "مدير الأرشفة القانونية",
      "مدقق العقود والمستندات",
      "مراجع داخلي للإجراءات",
      "مسؤول العقود طويلة الأمد",
      "رئيس لجنة الجودة"
    ],
    "less_suitable_roles_ar": [
      "أدوار الابتكار والمشاريع التجريبية.",
      "المبيعات العدوانية.",
      "الأدوار التي تتطلّب ارتجالاً دائماً.",
      "البيئات الفوضوية بلا هيكل."
    ],
    "recommendations_by_role_ar": {
      "for_founder_ar": {
        "title_ar": "توصيات للمؤسس",
        "intro_ar": "هذا الموظف هو حارس النظام في شركتك. استثمره في بناء الأسس المتينة طويلة الأمد.",
        "items_ar": [
          "كلّفه ببناء منظومة الإجراءات والسياسات الداخلية.",
          "اعتمد عليه في إدارة الملفات الاستراتيجية طويلة الأمد.",
          "استفد من ذاكرته المهنية في استرجاع السوابق والقرارات.",
          "امنحه وضوحاً في التوقّعات وتجنّب الغموض.",
          "احمِه من تحميله مسؤولياته الزائدة بسبب موثوقيته.",
          "أشركه في مراجعة قرارات التغيير قبل تنفيذها.",
          "قدّر انضباطه علنياً — الاعتراف يُعزّز ولاءه."
        ]
      },
      "for_counsels_ar": {
        "title_ar": "توصيات للمستشارين (Senior Counsel)",
        "intro_ar": "هذا الموظف مرجعكم الموثوق للإجراءات والوثائق. احترموا منهجيته واستفيدوا من دقته.",
        "items_ar": [
          "استعينوا به في توثيق القضايا وأرشفتها بدقة.",
          "اعتمدوا على ذاكرته في القضايا المشابهة السابقة.",
          "كلّفوه بإعداد القوائم المرجعية للملفات الكبرى.",
          "قدّموا له التعليمات مكتوبة ومُنظّمة.",
          "احترموا التزامه بالإجراءات ولا تتجاوزوها معه.",
          "استفيدوا من دقته في مراجعة العقود طويلة الأمد.",
          "ساعدوه في تقبّل التغيير بشرح المبرّرات بوضوح."
        ]
      },
      "for_partners_ar": {
        "title_ar": "توصيات للشركاء",
        "intro_ar": "مرشّح مثالي للشراكة في الجانب الإداري والتشغيلي للشركة.",
        "items_ar": [
          "ادرسوا تعيينه مسؤولاً عن الحوكمة والامتثال في الشركة.",
          "اعتمدوا عليه في بناء الأنظمة الداخلية وتطويرها.",
          "أشركوه في اللجان الدائمة (جودة، امتثال، مخاطر).",
          "طوّروا مرونته تدريجياً بمشاريع تحتوي تغييراً مُدروساً.",
          "امنحوه صلاحيات واضحة ومُوثّقة.",
          "احموه من الحمل الزائد بسبب موثوقيته.",
          "استفيدوا من دقته في بناء سمعة الشركة بالالتزام."
        ]
      },
      "for_peers_ar": {
        "title_ar": "توصيات للزملاء في نفس الرتبة",
        "intro_ar": "زميل موثوق قيّم، تعاملكم معه يحتاج احتراماً لأسلوبه المنضبط.",
        "items_ar": [
          "اعتمدوا عليه في تنظيم المشاريع المشتركة.",
          "قدّموا له التعليمات واضحة ومكتوبة.",
          "احترموا التزامه بالإجراءات ولا تضغطوا لتجاوزها.",
          "اشركوه في التخطيط المبكّر — يكره المفاجآت.",
          "استفيدوا من ذاكرته في استرجاع قرارات سابقة.",
          "لا تُفسّروا تحفّظه كعدم تعاون.",
          "كونوا واضحين في طلباتكم وتوقّعاتكم."
        ]
      },
      "for_managing_director_ar": {
        "title_ar": "توصيات للمدير الإداري",
        "intro_ar": "هذا الموظف سيكون أفضل حليف لك في الإدارة إذا وفّرت له الوضوح والنظام.",
        "items_ar": [
          "قدّم له تعليمات مكتوبة ومُنظّمة.",
          "احترم منهجيته في التنفيذ ولا تفرض اختصارات.",
          "أشركه في بناء الإجراءات الإدارية الجديدة.",
          "وفّر له بيئة مستقرة بدون تغييرات متكرّرة.",
          "اعتمد على موثوقيته في المهام الحساسة.",
          "اشرح له مبرّرات القرارات الإدارية.",
          "قدّم له اعترافاً بالتزامه — يُقدّره جداً."
        ]
      }
    },
    "red_flags_ar": [
      "توتّر مع التغييرات المتكرّرة — قد يحتاج للاستقرار.",
      "مقاومة علنية لإجراءات جديدة — حاور قبل الفرض.",
      "إرهاق من الحمل الزائد — لا يشكو عادةً.",
      "تراجع حماسه للعمل الروتيني — قد يعني الملل.",
      "انسحاب من النقاشات الاجتماعية."
    ],
    "motivation_triggers_ar": [
      "استقرار وظيفي وتقدير طويل الأمد.",
      "اعتراف بالانضباط والموثوقية.",
      "وضوح في المسؤوليات والصلاحيات.",
      "بيئة منظّمة بإجراءات محدّدة.",
      "مسار وظيفي واضح ومُحدّد."
    ],
    "leadership_potential_ar": "قيادته منظّمة صارمة، يُنتج فرقاً منضبطة وموثوقة. يحتاج لتطوير المرونة والانفتاح على الابتكار. أفضل في قيادة وحدات الامتثال والعمليات المستقرّة.",
    "development_recommendations_ar": [
      "تدريبات في إدارة التغيير والتكيّف.",
      "ورش في الابتكار والتفكير الإبداعي.",
      "تدريبات في المرونة والعفوية.",
      "ورش في التعبير العاطفي والتواصل.",
      "جلسات إرشاد لتوسيع أفقه الفكري."
    ]
  },
  "compatibility_notes_ar": {
    "works_well_with_ar": "يعمل بتناغم مع ISFJ لمشاركة الانضباط، ومع ENTJ الذي يحتاج منفّذاً موثوقاً.",
    "potential_friction_with_ar": "قد يصطدم مع ENFP وENTP بسبب عفويتهما، ومع ESTP بسبب المجازفة."
  }
}